<?xml version = '1.0' encoding = 'UTF-8'?>
<Relation class="oracle.dbtools.crest.model.design.logical.InheritanceRelation" name="Hierarchy_1" directorySegmentName="seg_0" id="D8381432-7442-6108-C82D-4343E0CC385D">
<createdBy>Usuario</createdBy>
<createdTime>2019-09-14 03:18:18 UTC</createdTime>
<ownerDesignName>data</ownerDesignName>
<engineerTo>
<item key="1CD80AED-4662-5F4B-3B68-9DEA21819FCB" value="true"/>
</engineerTo>
<identifying>false</identifying>
<nameOnSource>Super Type</nameOnSource>
<nameOnTarget>Sub Type</nameOnTarget>
<optionalSource>true</optionalSource>
<optionalTarget>true</optionalTarget>
<sourceEntity>1F96C579-2D80-0641-6462-18AC4A28C27F</sourceEntity>
<targetEntity>7605229D-161E-AE8F-4675-3130F33D2C60</targetEntity>
<transferable>true</transferable>
<deleteRule>NO ACTION</deleteRule>
</Relation>